p115fuse/__init__.py
p115fuse/__main__.py
p115fuse/py.typed
p115fuse-0.0.3.1.dist-info/METADATA
p115fuse-0.0.3.1.dist-info/WHEEL
p115fuse-0.0.3.1.dist-info/entry_points.txt
p115fuse-0.0.3.1.dist-info/licenses/LICENSE
p115fuse-0.0.3.1.dist-info/RECORD
